docparseai/__init__.py
docparseai/document_loader.py
docparseai/embed_patch.py
docparseai/embedder.py
docparseai/faiss_store.py
docparseai/text_splitter.py
docparseai-0.1.2.dist-info/licenses/LICENSE
docparseai-0.1.2.dist-info/METADATA
docparseai-0.1.2.dist-info/WHEEL
docparseai-0.1.2.dist-info/top_level.txt
docparseai-0.1.2.dist-info/RECORD
