Metadata-Version: 2.4
Name: docparseai
Version: 0.1.2
Summary: Document parsing, chunking, embedding, and vector retrieval made easy.
Author-email: Paul Onyekwelu <paulonyekweluo@gmail.com>
License: MIT
Project-URL: Homepage, https://docparseai.readthedocs.io/en/latest/
Project-URL: Repository, https://github.com/AgenticAiLabs/docparseai
Project-URL: Issues, https://github.com/AgenticAiLabs/docparseai/issues
Requires-Python: >=3.8
License-File: LICENSE
Requires-Dist: numpy
Requires-Dist: faiss-cpu
Requires-Dist: chardet
Requires-Dist: pymupdf
Requires-Dist: python-docx
Provides-Extra: embedding
Requires-Dist: sentence-transformers; extra == "embedding"
Provides-Extra: advanced
Requires-Dist: spacy; extra == "advanced"
Dynamic: license-file
